README
README.rst
setup.py
hostscli/__init__.py
hostscli/cli.py
hostscli/constants.py
hostscli/errors.py
hostscli/utils.py
hostscli.egg-info/PKG-INFO
hostscli.egg-info/SOURCES.txt
hostscli.egg-info/dependency_links.txt
hostscli.egg-info/entry_points.txt
hostscli.egg-info/requires.txt
hostscli.egg-info/top_level.txt
hostscli/websites/__init__.py
hostscli/websites/cloudflare.py
hostscli/websites/diply.py
hostscli/websites/facebook.py
hostscli/websites/google.py
hostscli/websites/instagram.py
hostscli/websites/linkedin.py
hostscli/websites/list_ads.py
hostscli/websites/list_malwares.py
hostscli/websites/list_misc.py
hostscli/websites/microsoft.py
hostscli/websites/pintrest.py
hostscli/websites/plus_google.py
hostscli/websites/test.py
hostscli/websites/twitter.py
hostscli/websites/whatsapp.py
hostscli/websites/youtube.py