Metadata-Version: 1.1
Name: hostscli
Version: 1.1.1
Summary: hostscli is a CLI tool to block / unblock websites using /etc/hosts
Home-page: https://github.com/dhilipsiva/hostscli
Author: dhilipsiva
Author-email: dhilipsiva@gmail.com
License: MIT
Keywords: hostscli hosts /etc/hosts block unblock websites
Platform: UNKNOWN
Classifier: Development Status :: 2 - Pre-Alpha
Classifier: Environment :: Console
Classifier: Intended Audience :: End Users/Desktop
Classifier: License :: OSI Approved :: MIT License
Classifier: Natural Language :: English
Classifier: Operating System :: POSIX
Classifier: Operating System :: Unix
Classifier: Programming Language :: Python
Classifier: Programming Language :: Python :: 2.7
Classifier: Programming Language :: Python :: 3.5
Classifier: Programming Language :: Python :: Implementation :: CPython
Classifier: Topic :: Internet
Classifier: Topic :: System :: Networking
Classifier: Topic :: System :: Networking :: Firewalls
Classifier: Topic :: Utilities
